nmodl_nightly-0.6.387.dist-info/entry_points.txt
nmodl_nightly-0.6.387.dist-info/RECORD
nmodl_nightly-0.6.387.dist-info/METADATA
nmodl_nightly-0.6.387.dist-info/WHEEL
nmodl_nightly-0.6.387.dist-info/licenses/LICENSE
nmodl_nightly-0.6.387.dist-info/licenses/AUTHORS.txt
nmodl/symtab.py
nmodl/ast.py
nmodl/_nmodl.cpython-39-x86_64-linux-gnu.so
nmodl/_binwrapper.py
nmodl/dsl.py
nmodl/__init__.py
nmodl/visitor.py
nmodl/ode.py
nmodl/.data/bin/nmodl
nmodl/.data/share/nmodl/nrnunits.lib
nmodl/.data/lib/libpywrapper.so
nmodl/.data/lib/cmake/nmodl/nmodlTargets.cmake
nmodl/.data/lib/cmake/nmodl/nmodlTargets-release.cmake
nmodl/.data/lib/cmake/nmodl/nmodlConfig.cmake
nmodl/.data/lib/cmake/nmodl/nmodlConfigVersion.cmake
nmodl/ext/example/passive.mod
nmodl/ext/example/hh.mod
nmodl/ext/example/exp2syn.mod
nmodl/ext/example/expsyn.mod
nmodl/ext/viz/index.html
nmodl/ext/viz/js/d3.min.js
nmodl/ext/viz/js/tree.js
nmodl/ext/viz/css/tree.css
