Metadata-Version: 2.1
Name: NMODL-nightly
Version: 0.6.387
Summary: NEURON Modeling Language Source-to-Source Compiler Framework
Author-Email: Blue Brain Project <bbp-ou-hpc@groupes.epfl.ch>
License:                                  Apache License
Requires-Python: >=3.9
Requires-Dist: find_libpython
Requires-Dist: sympy>=1.3
Requires-Dist: importlib-metadata; python_version < "3.9"
Requires-Dist: importlib-resources; python_version < "3.9"
Requires-Dist: pytest>=3.3.0; extra == "test"
Requires-Dist: pytest-cov; extra == "test"
Requires-Dist: numpy; extra == "test"
Requires-Dist: scipy; extra == "test"
Requires-Dist: jupyter-client; extra == "docs"
Requires-Dist: jupyter; extra == "docs"
Requires-Dist: myst_parser<2.0.0; extra == "docs"
Requires-Dist: mistune<3; extra == "docs"
Requires-Dist: nbconvert; extra == "docs"
Requires-Dist: nbsphinx>=0.3.2; extra == "docs"
Requires-Dist: sphinxcontrib-applehelp<1.0.3; extra == "docs"
Requires-Dist: sphinxcontrib-htmlhelp<=2.0.0; extra == "docs"
Requires-Dist: sphinx<6; extra == "docs"
Requires-Dist: sphinx-rtd-theme; extra == "docs"
Requires-Dist: docutils<0.20; extra == "docs"
Provides-Extra: test
Provides-Extra: docs
